uwsgi_env/__init__.py
uwsgi_env/utils.py
uwsgi_env-0.1.0.dist-info/DESCRIPTION.rst
uwsgi_env-0.1.0.dist-info/METADATA
uwsgi_env-0.1.0.dist-info/RECORD
uwsgi_env-0.1.0.dist-info/WHEEL
uwsgi_env-0.1.0.dist-info/metadata.json
uwsgi_env-0.1.0.dist-info/top_level.txt
