Metadata-Version: 1.1
Name: uwsgi-env
Version: 0.1.0
Summary: Automatically populate env with UWSGI_ variables and run uwsgi
Home-page: https://github.com/night-crawler/uwsgi-env
Author: night-crawler
Author-email: lilo.panic@gmail.com
License: MIT
Platform: UNKNOWN
Classifier: Environment :: Web Environment
Classifier: Intended Audience :: Developers
Classifier: Operating System :: OS Independent
Classifier: Programming Language :: Python
Classifier: Programming Language :: Python :: 3
Classifier: Programming Language :: Python :: 3.5
Classifier: License :: OSI Approved :: MIT License
Requires: uwsgi
